calendly/__init__.py
calendly/calendly.py
calendly/utils/constants.py
calendly/utils/requests.py
calendly-1.1.1.dist-info/LICENSE
calendly-1.1.1.dist-info/METADATA
calendly-1.1.1.dist-info/WHEEL
calendly-1.1.1.dist-info/top_level.txt
calendly-1.1.1.dist-info/RECORD
