Metadata-Version: 2.1
Name: calendly
Version: 1.1.1
Summary: A Python wrapper for the Calendly API  (https://developer.calendly.com/docs/)
Home-page: https://github.com/kevteg/calendly-python
Author: kevteg
Author-email: kevteg05@gmail.com
License: MIT
Keywords: Calendly python api
Platform: UNKNOWN
Classifier: License :: OSI Approved :: MIT License
Classifier: Programming Language :: Python :: 3.4
Classifier: Programming Language :: Python :: 3.5
Classifier: Programming Language :: Python :: 3.6
Classifier: Programming Language :: Python :: 3.7
Requires-Dist: requests
